ossctl.py
ossctl-0.1.0.dist-info/LICENSE
ossctl-0.1.0.dist-info/METADATA
ossctl-0.1.0.dist-info/WHEEL
ossctl-0.1.0.dist-info/top_level.txt
ossctl-0.1.0.dist-info/RECORD
