Metadata-Version: 2.1
Name: ossctl
Version: 0.1.0
Summary: oss command line controller
Author: wangziling100
Author-email: wangziling100@163.com
Classifier: Programming Language :: Python :: 3
Classifier: License :: OSI Approved :: MIT License
License-File: LICENSE
